README.md
setup.py
rancher/__init__.py
rancher/api.py
rancher/engine.py
rancher/errors.py
rancher/exceptions.py
rancher/models.py
rancher/utils.py
rancher.egg-info/PKG-INFO
rancher.egg-info/SOURCES.txt
rancher.egg-info/dependency_links.txt
rancher.egg-info/requires.txt
rancher.egg-info/top_level.txt