Metadata-Version: 1.0
Name: rancher
Version: 0.3.9
Summary: Python wrapper for rancher api
Home-page: https://github.com/mangeld/rancher_api
Author: Miguel Ángel Durán González
Author-email: hi@mangel.me
License: UNKNOWN
Platform: UNKNOWN
